zyntax/__init__.py
zyntax/cli.py
zyntax/main.py
zyntax/command_executor/__init__.py
zyntax/command_executor/executor.py
zyntax/interface/__init__.py
zyntax/interface/welcome.py
zyntax/nlp_engine/__init__.py
zyntax/nlp_engine/parser.py
zyntax-1.0.2.dist-info/licenses/LICENSE
zyntax-1.0.2.dist-info/METADATA
zyntax-1.0.2.dist-info/WHEEL
zyntax-1.0.2.dist-info/entry_points.txt
zyntax-1.0.2.dist-info/top_level.txt
zyntax-1.0.2.dist-info/RECORD
