Metadata-Version: 2.4
Name: zyntax
Version: 1.0.2
Summary: A smart terminal interface that understands natural language commands in English and Hinglish
Home-page: https://github.com/racxhit/Zyntax
Author: Rachit
Author-email: rachit.developer@gmail.com
Project-URL: Bug Reports, https://github.com/racxhit/Zyntax-NLP-Terminal/issues
Project-URL: Source, https://github.com/racxhit/Zyntax-NLP-Terminal
Project-URL: Documentation, https://github.com/racxhit/Zyntax-NLP-Terminal#readme
Keywords: nlp terminal cli natural-language command-line artificial-intelligence
Classifier: Development Status :: 3 - Alpha
Classifier: Intended Audience :: Developers
Classifier: Intended Audience :: System Administrators
Classifier: License :: OSI Approved :: MIT License
Classifier: Operating System :: OS Independent
Classifier: Programming Language :: Python :: 3
Classifier: Programming Language :: Python :: 3.8
Classifier: Programming Language :: Python :: 3.9
Classifier: Programming Language :: Python :: 3.10
Classifier: Programming Language :: Python :: 3.11
Classifier: Topic :: System :: Shells
Classifier: Topic :: Utilities
Classifier: Topic :: Scientific/Engineering :: Artificial Intelligence
Requires-Python: >=3.8
License-File: LICENSE
Requires-Dist: spacy<4.0.0,>=3.7.0
Requires-Dist: rapidfuzz<4.0.0,>=3.0.0
Requires-Dist: psutil<6.0.0,>=5.8.0
Requires-Dist: pytest<8.0.0,>=7.0.0
Dynamic: author
Dynamic: author-email
Dynamic: classifier
Dynamic: description
Dynamic: description-content-type
Dynamic: home-page
Dynamic: keywords
Dynamic: license-file
Dynamic: project-url
Dynamic: requires-dist
Dynamic: requires-python
Dynamic: summary
